avroserializer-0.1.0.dist-info/licenses/LICENSE
robotavroserializer/__init__.py
robotavroserializer/avroserializer.py
avroserializer-0.1.0.dist-info/METADATA
avroserializer-0.1.0.dist-info/WHEEL
avroserializer-0.1.0.dist-info/top_level.txt
avroserializer-0.1.0.dist-info/RECORD
