Metadata-Version: 2.4
Name: AvroSerializer
Version: 0.1.0
Summary: AvroSerializer is a serialization and RPC framework.
Home-page: https://avro.apache.org/
Author: Apache Software Foundation
Author-email: darioajr@gmail.com
License: Apache License 2.0
Classifier: Programming Language :: Python :: 3
Classifier: License :: OSI Approved :: Apache Software License
Classifier: Operating System :: OS Independent
Classifier: Framework :: Robot Framework :: Library
Requires-Python: >=3.7
License-File: LICENSE
Requires-Dist: robotframework
Requires-Dist: avro-python3
Provides-Extra: dev
Requires-Dist: pytest; extra == "dev"
Requires-Dist: build; extra == "dev"
Requires-Dist: twine; extra == "dev"
Dynamic: license-file
